qiskit_qcgpu_provider/__init__.py
qiskit_qcgpu_provider/job.py
qiskit_qcgpu_provider/qasm_simulator.py
qiskit_qcgpu_provider/simulatorerror.py
qiskit_qcgpu_provider/statevector_simulator.py
tests/__init__.py
tests/case.py
tests/test_qasm_simulator.py
tests/test_statevector_simulator.py
qiskit_qcgpu_provider-0.2.0.dist-info/LICENSE
qiskit_qcgpu_provider-0.2.0.dist-info/METADATA
qiskit_qcgpu_provider-0.2.0.dist-info/WHEEL
qiskit_qcgpu_provider-0.2.0.dist-info/top_level.txt
qiskit_qcgpu_provider-0.2.0.dist-info/RECORD
