Metadata-Version: 2.1
Name: qiskit-qcgpu-provider
Version: 0.2.0
Summary: An OpenCL based quantum computer simulator
Home-page: https://qcgpu.github.io
Author: Adam Kelly
Author-email: adamkelly2201@gmail.com
License: Apache 2.0
Platform: UNKNOWN
Classifier: Environment :: Console
Classifier: License :: OSI Approved :: Apache Software License
Classifier: Intended Audience :: Developers
Classifier: Intended Audience :: Science/Research
Classifier: Operating System :: Microsoft :: Windows
Classifier: Operating System :: MacOS
Classifier: Operating System :: POSIX :: Linux
Classifier: Programming Language :: Python :: 3.5
Classifier: Programming Language :: Python :: 3.6
Classifier: Topic :: Scientific/Engineering
Requires-Python: >=3.5
Requires-Dist: qiskit (>=0.7)
Requires-Dist: qcgpu (>=0.1.0)
